{
    "_updated": "2021-07-13",
    "category": [
        ""
    ],
    "curation": "https://nakamura196.github.io/shoen/curation/保-49.json",
    "description": [
        "挊田庄・笠田庄とも書く。紀ノ川中流域右岸にある荘園。西を穴伏川（静川）が流れる。"
    ],
    "label": "桛田庄",
    "latitude": [
        "34.2809428"
    ],
    "longitude": [
        "135.4835701"
    ],
    "manifest": "https://nakamura196.github.io/shoen/iiif/ee5715a004c2510b65ee646f50d1475b/manifest.json",
    "member": "https://nakamura196.github.io/shoen/iiif/ee5715a004c2510b65ee646f50d1475b/canvas/p1#xywh=9989,5815,1234,1274",
    "objectID": "91113bb18b1125570aa1507d3f0b0ae9",
    "thumbnail": "https://clioimg.hi.u-tokyo.ac.jp/viewer/api/image/idata/0M0/_105ho_/49/00000001.tif/9989,5815,1234,1274/200,/0/default.jpg",
    "図": [
        "高雄山神護寺領地紀伊国〓(かせ)田庄図"
    ],
    "架番号": [
        "保-49"
    ],
    "表記": [
        "桛田庄"
    ]
}