{
    "_updated": "2021-07-13",
    "category": [
        ""
    ],
    "curation": "https://nakamura196.github.io/shoen/curation/保-55.json",
    "description": [
        ""
    ],
    "label": "コシハ　一町アリ",
    "latitude": [
        ""
    ],
    "longitude": [
        ""
    ],
    "manifest": "https://nakamura196.github.io/shoen/iiif/921324076bdc341df8e29d752c55af47/manifest.json",
    "member": "https://nakamura196.github.io/shoen/iiif/921324076bdc341df8e29d752c55af47/canvas/p1#xywh=5038,4211,799,863",
    "objectID": "6477758ef819ac68389f35bc77818844",
    "thumbnail": "https://clioimg.hi.u-tokyo.ac.jp/viewer/api/image/idata/0M0/_105ho_/55/00000001.tif/5038,4211,799,863/200,/0/default.jpg",
    "図": [
        "箸喰庄差図"
    ],
    "架番号": [
        "保-55"
    ],
    "表記": [
        "コシハ　一町アリ"
    ]
}